[
  {"timestamp": 1699783499040, "price": "2900.00", "volume": "5.25"},
  {"timestamp": 1699783509040, "price": "2910.50", "volume": "3.85"},
  {"timestamp": 1699783519040, "price": "2925.75", "volume": "7.10"},
  {"timestamp": 1699783529040, "price": "2905.00", "volume": "4.45"},
  {"timestamp": 1699783539040, "price": "2920.75", "volume": "2.95"},
  {"timestamp": 1699783549040, "price": "2915.25", "volume": "6.75"},
  {"timestamp": 1699783559040, "price": "2908.50", "volume": "4.20"},
  {"timestamp": 1699783569040, "price": "2930.00", "volume": "8.50"},
  {"timestamp": 1699783579040, "price": "2935.75", "volume": "5.80"},
  {"timestamp": 1699783589040, "price": "2918.25", "volume": "3.35"},
  {"timestamp": 1699783599040, "price": "2940.50", "volume": "2.75"},
  {"timestamp": 1699783609040, "price": "2945.00", "volume": "6.95"},
  {"timestamp": 1699783619040, "price": "2928.25", "volume": "4.60"},
  {"timestamp": 1699783629040, "price": "2950.75", "volume": "3.10"},
  {"timestamp": 1699783639040, "price": "2955.00", "volume": "7.25"},
  {"timestamp": 1699783649040, "price": "2938.50", "volume": "4.40"},
  {"timestamp": 1699783659040, "price": "2932.25", "volume": "5.85"},
  {"timestamp": 1699783669040, "price": "2960.00", "volume": "2.90"},
  {"timestamp": 1699783679040, "price": "2958.75", "volume": "6.15"},
  {"timestamp": 1699783689040, "price": "2942.25", "volume": "4.55"},
  {"timestamp": 1699783699040, "price": "2948.50", "volume": "3.25"},
  {"timestamp": 1699783709040, "price": "2965.00", "volume": "5.70"},
  {"timestamp": 1699783719040, "price": "2962.25", "volume": "6.90"},
  {"timestamp": 1699783729040, "price": "2970.75", "volume": "3.05"},
  {"timestamp": 1699783739040, "price": "2968.50", "volume": "4.45"}
]